ttf2json/__init__.py
ttf2json/__main__.py
ttf2json/ttf2json.py
ttf2json/util/__init__.py
ttf2json/util/util.py
ttf2json-0.0.1.dist-info/licenses/LICENSE
ttf2json-0.0.1.dist-info/METADATA
ttf2json-0.0.1.dist-info/WHEEL
ttf2json-0.0.1.dist-info/top_level.txt
ttf2json-0.0.1.dist-info/RECORD
