Metadata-Version: 2.4
Name: ttf2json
Version: 0.0.1
Summary: A Python library for converting .ttf files to JSON for use with Three.js, supporting both CLI and programmatic usage
Author-email: maslke <maslke@outlook.com>
License: MIT License
Requires-Python: >=3.8
License-File: LICENSE
Dynamic: license-file
